{
  "Planktons": {
    "Cladocera": {
      "stressTemperatures": [0, 34, 37, 40],
      "decrease": ["Nee", "50-80%", "95-100%", "100%"]
    },
    "Copepoda": {
      "stressTemperatures": [0, 37, 40, 40.1],
      "decrease": ["Nee", "50%", "50-80%", "100%"]
    },
    "Rotatoria": {
      "stressTemperatures": [0, 37, 40, 40.1],
      "decrease": ["Nee", "0-50%", "50-80%", "100%"]
    },
    "Diatomeeen": {
      "stressTemperatures": [0, 34, 37, 40, 40.1],
      "decrease": ["Nee", "< 25%", "25-50%", "> 50%", "100%"]
    }
  },
  "Vissen": {
    "Blankvoorn": {
      "MaxTemperature": 27,
      "MinTemperature": 10,
      "MaxSpeed": 1.1,
      "MatingTemperature": "12-17"
    },
    "Baars": {
      "MaxTemperature": 24,
      "MinTemperature": 4,
      "MaxSpeed": 1.4,
      "MatingTemperature": "8-14"
    },
    "Brasem": {
      "MaxTemperature": 30.2,
      "MinTemperature": 4,
      "MaxSpeed": 0.8,
      "MatingTemperature": "14-17"
    },
    "Ruisvoorn": {
      "MaxTemperature": 31.2,
      "MinTemperature": 10,
      "MaxSpeed": 1.14,
      "MatingTemperature": "> 15"
    },
    "Pos": {
      "MaxTemperature": 28,
      "MinTemperature": 12,
      "MaxSpeed": 1.3,
      "MatingTemperature": "12-17"
    },
    "Zeelt": {
      "MaxTemperature": 31.2,
      "MinTemperature": 15,
      "MaxSpeed": 1.4,
      "MatingTemperature": "18-20"
    },
    "Alver": {
      "MaxTemperature": 30,
      "MinTemperature": 8,
      "MaxSpeed": 0.34,
      "MatingTemperature": "12-18"
    },
    "Riviergrondel": {
      "MaxTemperature": 27.2,
      "MinTemperature": 6,
      "MaxSpeed": 0.5,
      "MatingTemperature": "12-17"
    },
    "Winde": {
      "MaxTemperature": 26.6,
      "MinTemperature": 2,
      "MaxSpeed": 1.5,
      "MatingTemperature": "8-13"
    },
    "Snoekbaars": {
      "MaxTemperature": 35.4,
      "MinTemperature": 10,
      "MaxSpeed": 1.8,
      "MatingTemperature": "6-14"
    }
  }
}
